chunkator/__init__.py
chunkator/split.py
chunkator-0.0.11.dist-info/LICENSE
chunkator-0.0.11.dist-info/METADATA
chunkator-0.0.11.dist-info/WHEEL
chunkator-0.0.11.dist-info/top_level.txt
chunkator-0.0.11.dist-info/RECORD
