Metadata-Version: 2.1
Name: chunkator
Version: 0.0.11
Summary: A library for splitting text into sentences
Home-page: https://github.com/sahillihas/chunkator
Author: Sahil Sahil
Author-email: sahil.lihas@ymail.com
Classifier: Programming Language :: Python :: 3
Classifier: License :: OSI Approved :: MIT License
Classifier: Operating System :: OS Independent
Requires-Python: >=3.6
License-File: LICENSE
